gridgs/api/__init__.py
gridgs/api/client.py
gridgs/auth/client.py
gridgs/auth/token.py
gridgs/entity/frame.py
gridgs/entity/ground_station.py
gridgs/entity/horizontal_coords.py
gridgs/entity/satellite.py
gridgs/entity/session.py
gridgs/event/session_event.py
gridgs/event/subscriber.py
gridgs/mqtt/client.py
gridgs/mqtt/interface.py
gridgs-0.0.1.dist-info/LICENSE.txt
gridgs-0.0.1.dist-info/METADATA
gridgs-0.0.1.dist-info/WHEEL
gridgs-0.0.1.dist-info/top_level.txt
gridgs-0.0.1.dist-info/RECORD
